django_pg_agefilter/__init__.py
django_pg_agefilter-0.0.6.dist-info/DESCRIPTION.rst
django_pg_agefilter-0.0.6.dist-info/METADATA
django_pg_agefilter-0.0.6.dist-info/RECORD
django_pg_agefilter-0.0.6.dist-info/WHEEL
django_pg_agefilter-0.0.6.dist-info/metadata.json
django_pg_agefilter-0.0.6.dist-info/top_level.txt
