Metadata-Version: 2.0
Name: django-pg-agefilter
Version: 0.0.6
Summary: Helpers to leverage postgres's age filter from django
Home-page: https://github.com/davidszotten/django_pg_agefilter
Author: David Szotten
Author-email: davidszotten@gmail.com
License: MIT
Platform: UNKNOWN
Classifier: Environment :: Web Environment
Classifier: Framework :: Django
Classifier: Intended Audience :: Developers
Classifier: License :: OSI Approved :: MIT License
Classifier: Operating System :: OS Independent
Classifier: Programming Language :: Python
Classifier: Programming Language :: Python :: 2.7
Classifier: Topic :: Database
Requires-Dist: django (<2.1,>=1.8)
Requires-Dist: psycopg2
